mpv_http_router
