Metadata-Version: 1.1
Name: mpv-http-router
Version: 0.8.1
Summary: Redistribute MPV ipc server sockets
Home-page: https://github.com/voidpp/mpv-http-router
Author: Lajos Santa
Author-email: santa.lajos@gmail.com
License: MIT
Platform: UNKNOWN
Classifier: Development Status :: 4 - Beta
Classifier: Operating System :: OS Independent
Classifier: License :: OSI Approved :: MIT License
Classifier: Programming Language :: Python :: 3 :: Only
Classifier: Programming Language :: Python :: 3.6
Classifier: Programming Language :: Python :: 3.7
